mongodb_schema/__init__.py
mongodb_schema/cli.py
mongodb_schema/config.py
mongodb_schema/exceptions.py
mongodb_schema/exporter.py
mongodb_schema/utils.py
mongodb_schema-0.1.2.dist-info/METADATA
mongodb_schema-0.1.2.dist-info/WHEEL
mongodb_schema-0.1.2.dist-info/entry_points.txt
mongodb_schema-0.1.2.dist-info/top_level.txt
mongodb_schema-0.1.2.dist-info/RECORD
