Metadata-Version: 2.1
Name: mongodb-schema
Version: 0.1.2
Summary: A Python SDK for exporting MongoDB schema metadata
Home-page: https://github.com/karanbhatiakb/mongodb-schema/tree/master
Author: Karan Bhatia
Author-email: karanbhatia.kb27@gmail.com
Classifier: Programming Language :: Python :: 3
Classifier: License :: OSI Approved :: MIT License
Classifier: Operating System :: OS Independent
Requires-Python: >=3.6
Requires-Dist: pymongo
